odoo/addons/product_supplierinfo_disable_autocreation/README.rst
odoo/addons/product_supplierinfo_disable_autocreation/__init__.py
odoo/addons/product_supplierinfo_disable_autocreation/__manifest__.py
odoo/addons/product_supplierinfo_disable_autocreation/i18n/ca_ES.po
odoo/addons/product_supplierinfo_disable_autocreation/i18n/es.po
odoo/addons/product_supplierinfo_disable_autocreation/i18n/it.po
odoo/addons/product_supplierinfo_disable_autocreation/i18n/product_supplierinfo_disable_autocreation.pot
odoo/addons/product_supplierinfo_disable_autocreation/models/__init__.py
odoo/addons/product_supplierinfo_disable_autocreation/models/purchase_order.py
odoo/addons/product_supplierinfo_disable_autocreation/models/res_company.py
odoo/addons/product_supplierinfo_disable_autocreation/models/res_config_settings.py
odoo/addons/product_supplierinfo_disable_autocreation/readme/CONTRIBUTORS.md
odoo/addons/product_supplierinfo_disable_autocreation/readme/DESCRIPTION.md
odoo/addons/product_supplierinfo_disable_autocreation/readme/USAGE.md
odoo/addons/product_supplierinfo_disable_autocreation/static/description/icon.png
odoo/addons/product_supplierinfo_disable_autocreation/static/description/index.html
odoo/addons/product_supplierinfo_disable_autocreation/tests/__init__.py
odoo/addons/product_supplierinfo_disable_autocreation/tests/test_purchase_pricelist_disable.py
odoo/addons/product_supplierinfo_disable_autocreation/views/res_config_settings_views.xml
odoo_addon_product_supplierinfo_disable_autocreation-17.0.1.0.1.dist-info/METADATA
odoo_addon_product_supplierinfo_disable_autocreation-17.0.1.0.1.dist-info/WHEEL
odoo_addon_product_supplierinfo_disable_autocreation-17.0.1.0.1.dist-info/top_level.txt
odoo_addon_product_supplierinfo_disable_autocreation-17.0.1.0.1.dist-info/RECORD
